[[{"__type__":"cc.Prefab","_name":"tool_wood_long","data":{"__id__":1},"asyncLoadAssets":null},{"__type__":"cc.Node","_name":"wood","_components":[{"__type__":"cc.Sprite","node":{"__id__":1},"_spriteFrame":{"__uuid__":"fej57g8wNOHLTEsJzCIU/9"},"_sizeMode":0},{"__type__":"cc.RigidBody","node":{"__id__":1},"_linearDamping":0.8,"enabledContactListener":true},{"__type__":"cc.PhysicsBoxCollider","node":{"__id__":1},"_restitution":0.7,"_size":{"__type__":"cc.Size","width":100,"height":20}},{"__type__":"0c5c9iF+B9JZqXJxrxICdXZ","node":{"__id__":1},"blood_max":150,"blood":150,"armor":20,"crisp":1.1,"fragmentPrefab":{"__uuid__":"c7o4mSKktNoauyHhUQMH0o"},"deathAudio":{"__uuid__":"7fZ5FvA1tK/bwaJ/CVsV8I"},"type":"wood"}],"_prefab":{"__type__":"cc.PrefabInfo","root":{"__id__":1},"asset":{"__uuid__":"aaGkRtTnJGZID5TlrDONC9"},"fileId":"00EYDNYr9LZalKgdAiotFY"},"_contentSize":{"__type__":"cc.Size","width":100,"height":20}}],{"__type__":"cc.SpriteFrame","content":{"name":"wood_0","texture":"84Zg8X3ZVJQaxoKgeMNK7v","rect":[1,1,168,20],"offset":[0,0],"originalSize":[170,22]}}]